AgentGLM/AgentGLM.py
AgentGLM/__init__.py
AgentGLM-1.0.1.dist-info/LICENSE.txt
AgentGLM-1.0.1.dist-info/METADATA
AgentGLM-1.0.1.dist-info/WHEEL
AgentGLM-1.0.1.dist-info/top_level.txt
AgentGLM-1.0.1.dist-info/RECORD
