Metadata-Version: 2.1
Name: AgentGLM
Version: 1.0.1
Summary: llm agent engine package
Home-page: https://github.com/pypa/sampleproject
Author: VirginMariaJeremia
Author-email: VirginMariaJeremia@gmail.com
Classifier: Programming Language :: Python :: 3
Classifier: License :: OSI Approved :: MIT License
Classifier: Operating System :: OS Independent
License-File: LICENSE.txt
